Metadata-Version: 2.4
Name: xfastertransformer
Version: 2.1.2
Summary: Boost large language model inference performance on CPU platform.
Home-page: https://github.com/intel/xFasterTransformer
Author: xFasterTransformer
Author-email: xft.maintainer@intel.com
License: Apache 2.0
Keywords: LLM
Platform: x86_64
Requires-Python: >=3.8
License-File: LICENSE
Requires-Dist: torch<2.8.0,>=2.7.0
Dynamic: author
Dynamic: author-email
Dynamic: description
Dynamic: description-content-type
Dynamic: home-page
Dynamic: keywords
Dynamic: license
Dynamic: license-file
Dynamic: platform
Dynamic: requires-dist
Dynamic: requires-python
Dynamic: summary
